easypptx/__init__.py
easypptx/chart.py
easypptx/grid.py
easypptx/grid.py.bak
easypptx/image.py
easypptx/presentation.py
easypptx/pyplot.py
easypptx/reference_16x9.pptx
easypptx/reference_4x3.pptx
easypptx/slide.py
easypptx/table.py
easypptx/template.py
easypptx/template_generator.py
easypptx/text.py
easypptx-0.5.6.dist-info/METADATA
easypptx-0.5.6.dist-info/WHEEL
easypptx-0.5.6.dist-info/licenses/LICENSE
easypptx-0.5.6.dist-info/RECORD
