Metadata-Version: 2.4
Name: EasyPPTX
Version: 0.5.6
Summary: A Python library for easily creating and manipulating PowerPoint presentations programmatically with simple APIs.
Project-URL: Homepage, https://Ameyanagi.github.io/EasyPPTX/
Project-URL: Repository, https://github.com/Ameyanagi/EasyPPTX
Project-URL: Documentation, https://Ameyanagi.github.io/EasyPPTX/
Author-email: Ameyanagi <contact@ameyanagi.com>
License-File: LICENSE
Keywords: python
Classifier: Intended Audience :: Developers
Classifier: Programming Language :: Python
Classifier: Programming Language :: Python :: 3
Classifier: Programming Language :: Python :: 3.12
Classifier: Programming Language :: Python :: 3.13
Classifier: Topic :: Software Development :: Libraries :: Python Modules
Requires-Python: <4.0,>=3.12
Requires-Dist: matplotlib>=3.9.4
Requires-Dist: pandas>=2.2.3
Requires-Dist: python-pptx>=1.0.2
Requires-Dist: seaborn>=0.13.2
Requires-Dist: tomli-w>=1.0.0
Requires-Dist: tomli>=2.0.0
